cdstoolbox/__init__.py
cdstoolbox_remote-0.0.1.dist-info/METADATA
cdstoolbox_remote-0.0.1.dist-info/WHEEL
cdstoolbox_remote-0.0.1.dist-info/top_level.txt
cdstoolbox_remote-0.0.1.dist-info/zip-safe
cdstoolbox_remote-0.0.1.dist-info/RECORD
