Metadata-Version: 2.1
Name: cdstoolbox-remote
Version: 0.0.1
Summary: Experimental tool to run a workflow on the CDS Toolbox remotely
Home-page: https://software.ecmwf.int/stash/projects/CDS/repos/cdstoolbox-remote
Author: ECMWF
Author-email: software.support@ecmwf.int
License: Apache 2.0
Platform: UNKNOWN
Classifier: Development Status :: 3 - Alpha
Classifier: Intended Audience :: Developers
Classifier: Programming Language :: Python
Classifier: Programming Language :: Python :: 2
Classifier: Programming Language :: Python :: 2.7
Classifier: Programming Language :: Python :: 3
Classifier: Programming Language :: Python :: 3.4
Classifier: Programming Language :: Python :: 3.5
Classifier: Programming Language :: Python :: 3.6
Classifier: Programming Language :: Python :: Implementation :: CPython
Classifier: Programming Language :: Python :: Implementation :: PyPy
Classifier: Operating System :: OS Independent
Requires-Dist: cdsapi (>=0.2.3)
